README.txt
setup.py
collective/__init__.py
collective.navroottabs.egg-info/PKG-INFO
collective.navroottabs.egg-info/SOURCES.txt
collective.navroottabs.egg-info/dependency_links.txt
collective.navroottabs.egg-info/entry_points.txt
collective.navroottabs.egg-info/namespace_packages.txt
collective.navroottabs.egg-info/not-zip-safe
collective.navroottabs.egg-info/requires.txt
collective.navroottabs.egg-info/top_level.txt
collective/navroottabs/__init__.py
collective/navroottabs/configure.zcml
collective/navroottabs/interfaces.py
collective/navroottabs/navigation.py
collective/navroottabs/tests.py
collective/navroottabs/profiles/default/browserlayer.xml
collective/navroottabs/profiles/default/metadata.xml
docs/HISTORY.txt
docs/INSTALL.txt
docs/LICENSE.GPL
docs/LICENSE.txt