Metadata-Version: 1.0
Name: collective.navroottabs
Version: 0.1.0
Summary: Custom portal tabs for Plone folder that are INavigationRoot marked
Home-page: http://plone.org/products/collective.navroottabs
Author: RedTurtle Technology
Author-email: sviluppoplone@redturtle.net
License: GPL
Keywords: plone portal_tabs subsite plonegov
Platform: UNKNOWN
Classifier: Framework :: Plone
Classifier: Programming Language :: Python
Classifier: Development Status :: 4 - Beta
